Metadata-Version: 2.0
Name: Starter
Version: 0.4.2
Summary: Starter -- Create the skeleton for new projects.
Requires-Dist: Inirama (>=0.7.0)
Requires-Dist: Jinja2 (>=2.6)
Requires-Dist: oset (>=0.1.3)
